ranktier/__init__.py
ranktier-1.4.5.dist-info/LICENSE
ranktier-1.4.5.dist-info/METADATA
ranktier-1.4.5.dist-info/WHEEL
ranktier-1.4.5.dist-info/top_level.txt
ranktier-1.4.5.dist-info/RECORD
