Metadata-Version: 2.1
Name: ranktier
Version: 1.4.5
Summary: A Dota rank tier converter
Home-page: https://github.com/marcusmunch/ranktier
Author: Marcus Grünewald
Author-email: marcus@marcusmunch.dk
License: GPLv3
Classifier: Development Status :: 5 - Production/Stable
Classifier: Intended Audience :: Developers
Classifier: License :: OSI Approved :: GNU General Public License v3 (GPLv3)
Classifier: Natural Language :: English
Classifier: Operating System :: OS Independent
Classifier: Programming Language :: Python :: 3
Classifier: Programming Language :: Python :: 3.8
Classifier: Programming Language :: Python :: 3.9
Classifier: Programming Language :: Python :: 3.10
Classifier: Programming Language :: Python :: 3.11
License-File: LICENSE
